attrs_strict/__init__.py
attrs_strict/_commons.py
attrs_strict/_error.py
attrs_strict/_type_validation.py
attrs_strict/_version.py
attrs_strict/py.typed
attrs_strict-1.0.1.dist-info/LICENSE
attrs_strict-1.0.1.dist-info/METADATA
attrs_strict-1.0.1.dist-info/WHEEL
attrs_strict-1.0.1.dist-info/top_level.txt
attrs_strict-1.0.1.dist-info/RECORD
