Metadata-Version: 2.1
Name: attrs-strict
Version: 1.0.1
Summary: Runtime validators for attrs
Home-page: https://github.com/bloomberg/attrs-strict
Author: Erik-Cristian Seulean
Author-email: eseulean@bloomberg.net
License: Apache-2.0
Project-URL: Source, https://github.com/bloomberg/attrs-strict
Project-URL: Tracker, https://github.com/bloomberg/attrs-strict/issues
Project-URL: Documentation, https://github.com/bloomberg/attrs-strict/blob/main/README.md#attrs-runtime-validation
Classifier: Development Status :: 3 - Alpha
Classifier: Intended Audience :: Developers
Classifier: License :: OSI Approved :: Apache Software License
Classifier: Operating System :: MacOS :: MacOS X
Classifier: Operating System :: Microsoft :: Windows
Classifier: Operating System :: POSIX
Classifier: Programming Language :: Python :: 3
Classifier: Programming Language :: Python :: 3 :: Only
Classifier: Programming Language :: Python :: Implementation :: CPython
Classifier: Programming Language :: Python :: Implementation :: PyPy
Classifier: Topic :: Software Development :: Libraries
Classifier: Topic :: Software Development :: Testing
Classifier: Topic :: Utilities
Requires-Python: >=3.7
License-File: LICENSE
Requires-Dist: attrs >=22.2
Requires-Dist: typing-extensions >=4.5 ; python_version < "3.8"
Provides-Extra: docs
Requires-Dist: Sphinx >=6.1.3 ; extra == 'docs'
Provides-Extra: test
Requires-Dist: covdefaults >=2.3 ; extra == 'test'
Requires-Dist: pytest >=7.3.1 ; extra == 'test'
Requires-Dist: pytest-cov >=4 ; extra == 'test'
